horizon_hpe_storage/__init__.py
horizon_hpe_storage/overrides.py
horizon_hpe_storage/api/__init__.py
horizon_hpe_storage/api/barbican_api.py
horizon_hpe_storage/api/cinder_api.py
horizon_hpe_storage/api/hp_ssmc_api.py
horizon_hpe_storage/api/keystone_api.py
horizon_hpe_storage/api/barbicanClient/__init__.py
horizon_hpe_storage/api/barbicanClient/client.py
horizon_hpe_storage/api/barbicanClient/http.py
horizon_hpe_storage/api/cinderClient/__init__.py
horizon_hpe_storage/api/cinderClient/client.py
horizon_hpe_storage/api/cinderClient/http.py
horizon_hpe_storage/api/common/__init__.py
horizon_hpe_storage/api/common/data.py
horizon_hpe_storage/api/common/exceptions.py
horizon_hpe_storage/api/common/http.py
horizon_hpe_storage/api/common/http_v2.py
horizon_hpe_storage/api/common/ssh.py
horizon_hpe_storage/api/hpSSMCclient/__init__.py
horizon_hpe_storage/api/hpSSMCclient/client.py
horizon_hpe_storage/api/hpSSMCclient/http.py
horizon_hpe_storage/api/keystoneClient/__init__.py
horizon_hpe_storage/api/keystoneClient/client.py
horizon_hpe_storage/api/keystoneClient/http.py
horizon_hpe_storage/enabled/_999_hpe_storage_admin_panel.py
horizon_hpe_storage/storage_panel/__init__.py
horizon_hpe_storage/storage_panel/panel.py
horizon_hpe_storage/storage_panel/tabs.py
horizon_hpe_storage/storage_panel/urls.py
horizon_hpe_storage/storage_panel/version.py
horizon_hpe_storage/storage_panel/views.py
horizon_hpe_storage/storage_panel/backend_systems/__init__.py
horizon_hpe_storage/storage_panel/backend_systems/capability_tables.py
horizon_hpe_storage/storage_panel/backend_systems/license_tables.py
horizon_hpe_storage/storage_panel/backend_systems/tables.py
horizon_hpe_storage/storage_panel/backend_systems/tabs.py
horizon_hpe_storage/storage_panel/backend_systems/urls.py
horizon_hpe_storage/storage_panel/backend_systems/views.py
horizon_hpe_storage/storage_panel/config/__init__.py
horizon_hpe_storage/storage_panel/config/forms.py
horizon_hpe_storage_ui-2.4.2.dist-info/DESCRIPTION.rst
horizon_hpe_storage_ui-2.4.2.dist-info/METADATA
horizon_hpe_storage_ui-2.4.2.dist-info/RECORD
horizon_hpe_storage_ui-2.4.2.dist-info/WHEEL
horizon_hpe_storage_ui-2.4.2.dist-info/metadata.json
horizon_hpe_storage_ui-2.4.2.dist-info/pbr.json
horizon_hpe_storage_ui-2.4.2.dist-info/top_level.txt
