Metadata-Version: 2.0
Name: horizon-hpe-storage-ui
Version: 2.4.2
Summary: HPE Storage Plug-in for Horizon
Home-page: https://github.com/hpe-storage/horizon-hpe-storage-ui
Author: HPE Storage Cloud Team
Author-email: richard.hagarty@hpe.com
License: UNKNOWN
Platform: UNKNOWN
Classifier: Environment :: OpenStack
Classifier: Intended Audience :: Information Technology
Classifier: Intended Audience :: System Administrators
Classifier: License :: OSI Approved :: Apache Software License
Classifier: Operating System :: POSIX :: Linux
Classifier: Programming Language :: Python
Classifier: Programming Language :: Python :: 2
Classifier: Programming Language :: Python :: 2.7
Classifier: Programming Language :: Python :: 2.6
Classifier: Programming Language :: Python :: 3
Classifier: Programming Language :: Python :: 3.3
Classifier: Programming Language :: Python :: 3.4
Requires-Dist: cinderdiags (>=2.4.1)
Requires-Dist: python-barbicanclient (>=3.3.0)
